ml_audit/__init__.py
ml_audit/operations.py
ml_audit/recorder.py
ml_audit/utils.py
ml_audit/visualizer.py
ml_audit-0.1.6.dist-info/licenses/LICENSE
ml_audit-0.1.6.dist-info/METADATA
ml_audit-0.1.6.dist-info/WHEEL
ml_audit-0.1.6.dist-info/top_level.txt
ml_audit-0.1.6.dist-info/RECORD
