Metadata-Version: 2.4
Name: ml-audit
Version: 0.1.6
Summary: Solves Data Lineage Blindness by tracking granular preprocessing steps unlike standard experiment trackers.
Author: Shivogo John
License: MIT License
Requires-Python: >=3.9
License-File: LICENSE
Requires-Dist: numpy
Requires-Dist: pandas
Requires-Dist: matplotlib
Requires-Dist: scikit-learn
Dynamic: license-file
